soogo-2.0.1.dist-info/METADATA
soogo-2.0.1.dist-info/WHEEL
soogo-2.0.1.dist-info/entry_points.txt
soogo-2.0.1.dist-info/licenses/LICENSE
soogo/__init__.py
soogo/acquisition/__init__.py
soogo/acquisition/alternated_acquisition.py
soogo/acquisition/base.py
soogo/acquisition/coordinate_perturbation_over_nondominated.py
soogo/acquisition/endpoints_pareto_front.py
soogo/acquisition/gosac_sample.py
soogo/acquisition/maximize_distance.py
soogo/acquisition/maximize_ei.py
soogo/acquisition/minimize_mo_surrogate.py
soogo/acquisition/minimize_surrogate.py
soogo/acquisition/multiple_acquisition.py
soogo/acquisition/pareto_front.py
soogo/acquisition/target_value_acquisition.py
soogo/acquisition/transition_search.py
soogo/acquisition/utils.py
soogo/acquisition/weighted_acquisition.py
soogo/integrations/__init__.py
soogo/integrations/nomad.py
soogo/integrations/pymoo.py
soogo/model/__init__.py
soogo/model/base.py
soogo/model/gp.py
soogo/model/rbf.py
soogo/model/rbf_kernel.py
soogo/optimize/__init__.py
soogo/optimize/bayesian_optimization.py
soogo/optimize/cptv.py
soogo/optimize/dycors.py
soogo/optimize/fsapso.py
soogo/optimize/gosac.py
soogo/optimize/multistart_msrs.py
soogo/optimize/result.py
soogo/optimize/shebo.py
soogo/optimize/socemo.py
soogo/optimize/surrogate_optimization.py
soogo/optimize/utils.py
soogo/sampling.py
soogo/termination.py
soogo/utils.py
soogo-2.0.1.dist-info/RECORD
