Metadata-Version: 2.1
Name: soogo
Version: 2.0.1
Summary: Surrogate-based 0-th Order Global Optimization for black-box problems
Keywords: optimization,surrogate,black-box,gradient-free
Author: Byron Selvage
Author-Email: Weslley da Silva Pereira <weslley.dasilvapereira@nrel.gov>
Maintainer-Email: Weslley da Silva Pereira <weslley.dasilvapereira@nrel.gov>
License: Copyright (c) 2025 Alliance for Energy Innovation, LLC
Classifier: License :: OSI Approved :: GNU General Public License (GPL)
Classifier: Programming Language :: Python
Classifier: Programming Language :: Python :: 3
Project-URL: Homepage, https://github.com/NREL/soogo
Project-URL: Docs, https://nrel.github.io/soogo
Requires-Python: >=3.9
Requires-Dist: numpy
Requires-Dist: scipy
Requires-Dist: pymoo
Requires-Dist: scikit-learn
Requires-Dist: autograd
Requires-Dist: networkx
